<?xml version = '1.0' encoding = 'UTF-8'?>
<TableProxyOraclev11g class="oracle.dbtools.crest.model.design.storage.oracle.v11g.TableProxyOraclev11g" name="SELLINFO" directorySegmentName="seg_0" id="1766DF19-A2E3-CAD3-71B1-0ABF58192BCE">
<createdBy>dewey</createdBy>
<createdTime>2023-04-19 01:01:40 UTC</createdTime>
<ownerDesignName>230419</ownerDesignName>
<schemaObject>58DA281E-5F9B-09F7-4007-C730D7C472A6</schemaObject>
<logging>YES</logging>
<partitionedRowMovement>DISABLE</partitionedRowMovement>
<segment>84BE2D7F-1AF5-1A07-8E80-A474BCE998E5</segment>
<tableSpace>3113D635-C4BC-D9F8-9C0F-81021DF4C78F</tableSpace>
<temporaryChanged>false</temporaryChanged>
<accessDriverType>oracle_loader</accessDriverType>
<rejectLimit></rejectLimit>
<columnProxies itemClass="oracle.dbtools.crest.model.design.storage.oracle.v12c.ColumnProxyOraclev12c">
<ColumnProxy name="SELLDATE" id="0B1463EA-6D57-6E98-12CE-EBDE8E04267A">
<createdBy>dewey</createdBy>
<createdTime>2023-04-19 01:01:40 UTC</createdTime>
<ownerDesignName>230419</ownerDesignName>
<defaultValue>Sysdate</defaultValue>
</ColumnProxy>
<ColumnProxy name="QTT" id="1D0D7E33-08F6-9590-0ED6-2B2E754B4DD6">
<createdBy>dewey</createdBy>
<createdTime>2023-04-19 01:01:40 UTC</createdTime>
<ownerDesignName>230419</ownerDesignName>
</ColumnProxy>
<ColumnProxy name="PROMICEDATE" id="26F43B09-720A-A9E3-07CE-3795B8BD079C">
<createdBy>dewey</createdBy>
<createdTime>2023-04-19 01:01:40 UTC</createdTime>
<ownerDesignName>230419</ownerDesignName>
</ColumnProxy>
<ColumnProxy name="CODE" id="2D4155CB-2A9E-0E22-2E38-3359AB09F77C">
<createdBy>dewey</createdBy>
<createdTime>2023-04-19 01:01:40 UTC</createdTime>
<ownerDesignName>230419</ownerDesignName>
</ColumnProxy>
<ColumnProxy name="CUSTOMNO" id="2D8C30EA-1FE1-B433-903B-92D7DA0334B4">
<createdBy>dewey</createdBy>
<createdTime>2023-04-19 01:01:40 UTC</createdTime>
<ownerDesignName>230419</ownerDesignName>
</ColumnProxy>
<ColumnProxy name="EMPNO" id="6B0A7504-7145-9B25-A9F5-DB09E1E9B6D0">
<createdBy>dewey</createdBy>
<createdTime>2023-04-19 01:01:40 UTC</createdTime>
<ownerDesignName>230419</ownerDesignName>
</ColumnProxy>
<ColumnProxy name="SELLNO" id="7B3FA51E-5CD7-8527-26AA-BED7359C056C">
<createdBy>dewey</createdBy>
<createdTime>2023-04-19 01:01:40 UTC</createdTime>
<ownerDesignName>230419</ownerDesignName>
</ColumnProxy>
<ColumnProxy name="COUPONCODE" id="A1305462-A307-3554-46BC-7DB909DBAE3A">
<createdBy>dewey</createdBy>
<createdTime>2023-04-19 01:01:40 UTC</createdTime>
<ownerDesignName>230419</ownerDesignName>
</ColumnProxy>
<ColumnProxy name="GOODNO" id="BB71DBC2-4F0E-1ABF-F89C-6487BD4ED6BC">
<createdBy>dewey</createdBy>
<createdTime>2023-04-19 01:01:40 UTC</createdTime>
<ownerDesignName>230419</ownerDesignName>
</ColumnProxy>
<ColumnProxy name="SELLSTATUS" id="EDF6ACD4-6514-CD08-42A0-2305273E1395">
<createdBy>dewey</createdBy>
<createdTime>2023-04-19 01:01:40 UTC</createdTime>
<ownerDesignName>230419</ownerDesignName>
<defaultValue>0</defaultValue>
</ColumnProxy>
<ColumnProxy name="REALPRICE" id="F8A8A191-0AEF-5049-1342-25CB7BB8989C">
<createdBy>dewey</createdBy>
<createdTime>2023-04-19 01:01:40 UTC</createdTime>
<ownerDesignName>230419</ownerDesignName>
</ColumnProxy>
</columnProxies>
<foreignKeys>
<ForeignKey class="oracle.dbtools.crest.model.design.storage.oracle.v10g.FKProxyOraclev10g" name="FK_USECOUPON_TO_SELLINFO" id="629A2644-558A-8110-0E81-C43032E29A89">
<createdBy>dewey</createdBy>
<createdTime>2023-04-19 01:01:42 UTC</createdTime>
<ownerDesignName>230419</ownerDesignName>
</ForeignKey>
<ForeignKey class="oracle.dbtools.crest.model.design.storage.oracle.v10g.FKProxyOraclev10g" name="FK_CAMPINFO_TO_SELLINFO" id="6AE397FA-CC94-A77E-5B30-875259CD1A98">
<createdBy>dewey</createdBy>
<createdTime>2023-04-19 01:01:42 UTC</createdTime>
<ownerDesignName>230419</ownerDesignName>
</ForeignKey>
<ForeignKey class="oracle.dbtools.crest.model.design.storage.oracle.v10g.FKProxyOraclev10g" name="FK_CUSTOMINFO_TO_SELLINFO" id="95C538B6-5963-68D3-125B-58232CCFAF9E">
<createdBy>dewey</createdBy>
<createdTime>2023-04-19 01:01:42 UTC</createdTime>
<ownerDesignName>230419</ownerDesignName>
</ForeignKey>
<ForeignKey class="oracle.dbtools.crest.model.design.storage.oracle.v10g.FKProxyOraclev10g" name="FK_GOODINFO_TO_SELLINFO" id="A6E9F8C3-39E2-E059-AF74-88A47626CE20">
<createdBy>dewey</createdBy>
<createdTime>2023-04-19 01:01:42 UTC</createdTime>
<ownerDesignName>230419</ownerDesignName>
</ForeignKey>
</foreignKeys>
</TableProxyOraclev11g>