<?xml version = '1.0' encoding = 'UTF-8'?>
<Diagram class="oracle.dbtools.crest.swingui.datatypes.DPVDataTypes" id="CDFE2072-04F4-D8CA-AD5D-08E0A195A5B9">
<createdBy>dewey</createdBy>
<modifiedBy>dewey</modifiedBy>
<createdTime>2023-05-07 01:48:57 UTC</createdTime>
<autoRoute>false</autoRoute>
<boxInbox>true</boxInbox>
<showLegend>false</showLegend>
<showLabels>true</showLabels>
<showRelAttributes>false</showRelAttributes>
<gridEnabled>false</gridEnabled>
<showGrid>false</showGrid>
<diagramColor>-1</diagramColor>
<display>false</display>
<notation>1</notation>
<objectViews>
<OView class="oracle.dbtools.crest.swingui.datatypes.TVStructuredType" oid="47E390DE-0671-C4B1-8428-0F45CBEE18F8" otype="StructuredType" vid="B3380425-94D7-0B2E-8B7F-CA2F6CB25201">
<hideElementsInCurrentOnly>false</hideElementsInCurrentOnly>
<bounds x="20" y="20" width="108" height="39"/>
</OView>
<OView class="oracle.dbtools.crest.swingui.datatypes.TVStructuredType" oid="F72C39E0-D1CA-8821-2AD7-A1E95A37D3D1" otype="StructuredType" vid="C8D4BDF8-D082-B6E0-3687-CC4E6BADA876">
<hideElementsInCurrentOnly>false</hideElementsInCurrentOnly>
<bounds x="178" y="20" width="78" height="39"/>
</OView>
</objectViews>
</Diagram>